setup.py
pytlab/__init__.py
pytlab/pytlab.py
pytlab.egg-info/PKG-INFO
pytlab.egg-info/SOURCES.txt
pytlab.egg-info/dependency_links.txt
pytlab.egg-info/requires.txt
pytlab.egg-info/top_level.txt